termitext/__init__.py
termitext-0.2.0.dist-info/LICENSE
termitext-0.2.0.dist-info/WHEEL
termitext-0.2.0.dist-info/METADATA
termitext-0.2.0.dist-info/RECORD
