Metadata-Version: 2.1
Name: termitext
Version: 0.2.0
Summary: Color and format text in the console
Author: Yek
Author-email: gwojtysiak34@gmail.com
Requires-Python: >=3.8,<4.0
Classifier: Programming Language :: Python :: 3
Classifier: Programming Language :: Python :: 3.8
